{
    "Timo": {
        "Goals": 7,
        "Assists": 14,
        "Shots on Goal": 74,
        "Penalties in Minutes": 8,
        "Plus / Minus": 13,
        "Time Played in Minutes": 437.2,
        "Save Percentage": 0.833,
        "Goals Against Average": 4.13
    },
    "Leevon": {
        "Goals": 4,
        "Assists": 6,
        "Shots on Goal": 36,
        "Penalties in Minutes": 8,
        "Plus / Minus": -6,
        "Time Played in Minutes": 318.15,
        "Save Percentage": 0.88,
        "Goals Against Average": 3.0
    },
    "Alasdair": {
        "Goals": 8,
        "Assists": 13,
        "Shots on Goal": 50,
        "Penalties in Minutes": 6,
        "Plus / Minus": 7,
        "Time Played in Minutes": 288.3,
        "Save Percentage": 0.917,
        "Goals Against Average": 2.54
    },
    "Liam": {
        "Goals": 3,
        "Assists": 5,
        "Shots on Goal": 33,
        "Penalties in Minutes": 10,
        "Plus / Minus": -2,
        "Time Played in Minutes": 272.95,
        "Save Percentage": 0.976,
        "Goals Against Average": 1.0
    },
    "John": {
        "Goals": 1,
        "Assists": 5,
        "Shots on Goal": 42,
        "Penalties in Minutes": 12,
        "Plus / Minus": -10,
        "Time Played in Minutes": 316.3,
        "Save Percentage": 0.935,
        "Goals Against Average": 2.02
    },
    "Carsten": {
        "Goals": 5,
        "Assists": 14,
        "Shots on Goal": 58,
        "Penalties in Minutes": 8,
        "Plus / Minus": 5,
        "Time Played in Minutes": 381.4,
        "Save Percentage": 0.925,
        "Goals Against Average": 2.54
    }
}